async_search_client/__init__.py
async_search_client-0.9.0.dist-info/LICENSE
async_search_client-0.9.0.dist-info/WHEEL
async_search_client-0.9.0.dist-info/METADATA
async_search_client-0.9.0.dist-info/RECORD
