Metadata-Version: 2.1
Name: async-search-client
Version: 0.9.0
Summary: async-search-client is now meilisearch-python-async
Home-page: https://github.com/sanders41/meilisearch-python-async
License: MIT
Keywords: meilisearch,async
Author: Paul Sanders
Author-email: psanders1@gmail.com
Requires-Python: >=3.7,<4.0
Classifier: Development Status :: 7 - Inactive
Classifier: License :: OSI Approved :: MIT License
Classifier: Programming Language :: Python :: 3
Classifier: Programming Language :: Python :: 3.7
Classifier: Programming Language :: Python :: 3.8
Classifier: Programming Language :: Python :: 3.9
Requires-Dist: meilisearch-python-async (>=0.10.0,<0.11.0)
Project-URL: Documentation, https://github.com/sanders41/meilisearch-python-async
Project-URL: Repository, https://github.com/sanders41/meilisearch-python-async
